telepop_env/__init__.py
telepop_env/core.py
telepop_env-0.1.4.dist-info/licenses/LICENSE
telepop_env-0.1.4.dist-info/METADATA
telepop_env-0.1.4.dist-info/WHEEL
telepop_env-0.1.4.dist-info/top_level.txt
telepop_env-0.1.4.dist-info/RECORD
