Metadata-Version: 2.4
Name: telepop_env
Version: 0.1.4
Summary: Tiny zero-dependency environment variable loader with type casting and .env.example generation
Author-email: Ivan Goncharov <telepop.iv@gmail.com>
License: MIT
Requires-Python: >=3.7
License-File: LICENSE
Dynamic: license-file
